Workbook

Sheet Cover
A1: Operating Cash Cycles
A2: Intro to Forecasting
A5: Created by: | B5: Ellen Burnes

Sheet Fin Statements
A1: (see Leach and Melicher, p. 220)
A2: INCOME STATEMENT | G2: BALANCE SHEET
C3: 2020 | D3: 2021 | G3: ASSETS | H3: 2020 | I3: 2021
A4: Revenue | C4: 900000 | D4: =1500000 -> 1500000 | G4: Current Assets
A5: COGS | C5: 540000 | D5: 900000 | G5: Cash | H5: 50000 | I5: 20000
A6: Gross Profit | C6: =C4-C5 -> 360000 | D6: =D4-D5 -> 600000 | G6: A/R | H6: 200000 | I6: 280000
A7: OPEX | G7: Inventories | H7: 400000 | I7: 500000
A8: Marketing | C8: 90000 | D8: 150000 | G8: Total Current Assets | H8: =SUM(H5:H7) -> 650000 | I8: =SUM(I5:I7) -> 800000
A9: General & Administrative | C9: 175000 | D9: 175000 | G9: Fixed Assets
A10: R&D | C10: 75000 | D10: 75000 | G10: Gross Fixed Assets | H10: 450000 | I10: 540000
A11: EBITDA | C11: =C6-C8-C9-C10 -> 20000 | D11: =D6-D8-D9-D10 -> 200000 | G11: Accumulated Depreciation | H11: 100000 | I11: 140000
A12: Depreciation | C12: 40000 | D12: 40000 | G12: Net Fixed Assets | H12: =H10-H11 -> 350000 | I12: =I10-I11 -> 400000
A13: EBIT | C13: =C11-C12 -> -20000 | D13: =D11-D12 -> 160000 | G13: Total Assets | H13: =H8+H12 -> 1000000 | I13: =I8+I12 -> 1200000
A14: Interest | C14: 45000 | D14: 60000 | G14: LIABILITIES & SE
A15: Pre Tax Income | C15: =C13-C14 -> -65000 | D15: =D13-D14 -> 100000 | G15: Current Liabilities
A16: Taxes | B16: 0.25 | C16: =IF(C15>0,$B$16*C15,0) -> 0 | D16: =IF(D15>0,$B$16*D15,0) -> 25000 | G16: A/P | H16: 130000 | I16: 160000
A17: Net Income | C17: =C15-C16 -> -65000 | D17: =D15-D16 -> 75000 | G17: Bank Notes | H17: 140000 | I17: 170000
G18: Total Current Liabilities | H18: =H16+H17 -> 270000 | I18: =I16+I17 -> 330000
C19: =_xlfn.FORMULATEXT(C16) -> =IF(C15>0,$B$16*C15,0) | G19: Long Term Liabilities
G20: Debt | H20: 300000 | I20: 400000
G21: Shareholders' Equity
G22: Invested Capital | H22: 350000 | I22: 350000
G23: Retained Earnings | H23: 80000 | I23: 120000
G24: Total Liabilities & SE | H24: =H18+H20+H22+H23 -> 1000000 | I24: =I18+I20+I22+I23 -> 1200000

Sheet Operating Cycle_Blank
A1: Operating Cycle = Inventory Period + A/R Period
A3: 1) inventory Period
A4: Inventory Period = 365/inventory turnover
A6: Inventory Turnover = COGS/Inventory
B7: 2020 | C7: 2021
A8: COGS
A9: Inventory =
A11: Inventory Turnover
A14: Inventory Period
A17: 2) Receivables (A/R) Period
A18: Receivables Period = 365/Receivables Turnover
A20: Receivables Turnover = Credit Sales/A/R | E20: **You have to KNOW or ASSUME the % total Sales that are credit.
B21: 2020 | C21: 2021 | E21: For this example, we will assume 100% are credit
A22: Credit Sales =
A23: A/R
A25: Receivables Turnover
A27: Receivables Period
A31: OPERATING CYCLE = | D31: DAYS

Sheet Cash Cycle_Blank
A1: Cash Cycle = Operating Cycle - A/P Period
A3: We have Operating Cycle
A5: A/P Period = | B5: 365/Payables Turnover
A7: Payables Turnover = | B7: COGS/A/P
A9: COGS
A10: A/P
A12: Payables Turnover
A14: A/P Period | D14: days
B16: 2020 | C16: 2021
A17: CASH CYCLE

Sheet Forecast_Blank
J1: growth scenarios
A2: INCOME STATEMENT | I2: base | J2: 0.1 | K2: 0.2 | L2: 0.3 | M2: 0.4
B3: Assump. | C3: 2020 | D3: 2021 | E3: 2022 | F3: 2023
A4: Revenue | B4: 0.25 | C4: 900000 | D4: =1500000 -> 1500000
A5: COGS | B5: =C5/C4 -> 0.6 | C5: 540000 | D5: 900000
A6: Gross Profit
A7: OPEX
A8: Marketing | B8: =C8/C4 -> 0.1 | C8: 90000 | D8: 150000
A9: General & Administrative | C9: 175000 | D9: 175000
A10: R&D | C10: 75000 | D10: 75000
A11: EBITDA
A12: Depreciation | C12: 40000 | D12: 40000
A13: EBIT
A14: Interest | C14: 45000 | D14: 60000
A15: Pre Tax Income
A16: Taxes | B16: 0.25
A17: Net Income

Sheet Operating Cycle
A1: Operating Cycle = Inventory Period + A/R Period
A3: Inventory Period = 365/inventory turnover
A5: Inventory Turnover = COGS/ Inventory
B6: 2021 | C6: 2021
A7: COGS = | B7: ='Fin Statements'!C5 -> 540000 | C7: ='Fin Statements'!D5 -> 900000
A8: Inventory = | B8: ='Fin Statements'!H7 -> 400000 | C8: ='Fin Statements'!I7 -> 500000
A10: Inventory Turnover | B10: =B7/B8 -> 1.35 | C10: =C7/C8 -> 1.8
A13: Inventory Period | B13: =365/B10 -> 270.37037 | C13: =365/C10 -> 202.77778
A17: Receivables Period = 365/Receivables Turnover
A19: Receivables Turnover = Credit Sales/A/R | E19: **You have to KNOW opr ASSUME the % total Sales that are credit.
B20: 2020 | C20: 2021 | E20: For this example, we will assume 100% are credit
A21: Credit Sales = | B21: ='Fin Statements'!C4 -> 900000 | C21: ='Fin Statements'!D4 -> 1500000
A22: A/R | B22: ='Fin Statements'!H6 -> 200000 | C22: ='Fin Statements'!I6 -> 280000
A24: Receivables Turnover | B24: =B21/B22 -> 4.5 | C24: =C21/C22 -> 5.3571429
A26: Receivables Period | B26: =365/B24 -> 81.111111 | C26: =365/C24 -> 68.133333
B29: 2020 | C29: 2021
A30: OPERATING CYCLE = | B30: =B13+B26 -> 351.48148 | C30: =C13+C26 -> 270.91111

Sheet Cash Cycle
A1: Cash Cycle = Operating Cycle - A/P Period
A3: We have Operating Cycle
A5: A/P Period = | B5: 365/Payables Turnover
A7: Payables Turnover = | B7: COGS/A/P
B8: 2020 | C8: 2021
A9: COGS = | B9: ='Fin Statements'!C5 -> 540000 | C9: ='Fin Statements'!D5 -> 900000
A10: A/P | B10: ='Fin Statements'!H16 -> 130000 | C10: ='Fin Statements'!I16 -> 160000
A12: Payables Turnover | B12: =B9/B10 -> 4.1538462 | C12: =C9/C10 -> 5.625
A14: A/P Period | B14: =365/B12 -> 87.87037 | C14: =365/C12 -> 64.888889
B16: 2020 | C16: 2021
A17: CASH CYCLE | B17: ='Operating Cycle'!B30-'Cash Cycle'!B14 -> 263.61111 | C17: ='Operating Cycle'!C30-'Cash Cycle'!C14 -> 206.02222

Sheet Forecast_
A2: INCOME STATEMENT
C3: 2020 | D3: 2021 | E3: 2022 | F3: 2023
A4: Revenue | B4: 0.25 | C4: 900000 | D4: =1500000 -> 1500000 | E4: =D4*(1+$B$4) -> 1875000 | F4: =E4*(1+$B$4) -> 2343750
A5: COGS | B5: =C5/C4 -> 0.6 | C5: 540000 | D5: 900000 | E5: =$B$5*E4 -> 1125000 | F5: =$B$5*F4 -> 1406250
A6: Gross Profit | E6: =E4-E5 -> 750000 | F6: =F4-F5 -> 937500
A7: OPEX
A8: Marketing | B8: =C8/C4 -> 0.1 | C8: 90000 | D8: 150000 | E8: =$B$8*E4 -> 187500 | F8: =$B$8*F4 -> 234375
A9: General & Administrative | C9: 175000 | D9: 175000 | E9: =D9 -> 175000 | F9: =E9 -> 175000 | L9: Revenue Growth Rate Scenarios
A10: R&D | C10: 75000 | D10: 75000 | E10: =D10 -> 75000 | F10: =E10 -> 75000 | K10: Base | L10: 0.1 | M10: 0.2 | N10: 0.3 | O10: 0.4
A11: EBITDA | E11: =E6-E8-E9-E10 -> 312500 | F11: =F6-F8-F9-F10 -> 453125 | J11: Revenue | K11: =F17 -> 264843.75 | L11: 145875 | M11: 223500 | N11: 307875 | O11: 399000
A12: Depreciation | C12: 40000 | D12: 40000 | E12: 40000 | F12: 40000
A13: EBIT | E13: =E11-E12 -> 272500 | F13: =F11-F12 -> 413125
A14: Interest | C14: 45000 | D14: 60000 | E14: =D14 -> 60000 | F14: =E14 -> 60000
A15: Pre Tax Income | E15: =E13-E14 -> 212500 | F15: =F13-F14 -> 353125
A16: Taxes | B16: 0.25 | E16: =$B$16*E15 -> 53125 | F16: =$B$16*F15 -> 88281.25
A17: Net Income | E17: =E15-E16 -> 159375 | F17: =F15-F16 -> 264843.75
F18: NO DECIMALS!!!
