Workbook

Sheet Title Page
B2: This spreadsheet supports STUDENT analysis of the case “Bob’s Baloney” (UVA-F-1942).
A4: This spreadsheet was prepared by Michael Schill, Sponsors Professor of Business Administration. Copyright © 2020 by the University of Virginia Darden School Foundation, Charlottesville, VA. All rights reserved. For customer service inquiries, send an email tosales@dardenbusinesspublishing.com. No part of this publication may be reproduced, stored in a retrieval system, posted to the internet, or transmitted in any form or by any means—electronic, mechanical, photocopying, recording, or otherwise—without the permission of the Darden School Foundation. This publication is protected by copyright and may not be uploaded in whole or part to any AI, large language model, or similar system, or to any related database. Our goal is to publish materials of the highest quality, so please submit any errata to editorial@dardenbusinesspublishing.com.
A5: Rev. Jan. 30, 2024

Sheet Exhibit 1
A1: Exhibit 1
A2: Bob’s Baloney
A3: Financial Statements for Bob’s Baloney (in millions of US dollars)
C5: 2015 | D5: 2016 | E5: 2017 | F5: 2018 | G5: 2019
B6: Revenue | C6: 190.5 | D6: 185.6 | E6: 209.8 | F6: 248.3 | G6: 271.8
B7: Cost of Goods Sold | C7: 136.9 | D7: 135.8 | E7: 156.8 | F7: 189.3 | G7: 212.1
B8: Gross Profit | C8: =C6-C7 -> 53.6 | D8: =D6-D7 -> 49.8 | E8: =E6-E7 -> 53 | F8: =F6-F7 -> 59 | G8: =G6-G7 -> 59.7
B9: Selling and General Expenses | C9: 18.8 | D9: 28.8 | E9: 38.3 | F9: 47.5 | G9: 47
B10: Operating Profit | C10: =C8-C9 -> 34.8 | D10: =D8-D9 -> 21 | E10: =E8-E9 -> 14.7 | F10: =F8-F9 -> 11.5 | G10: =G8-G9 -> 12.7
B11: Net Interest Expense | C11: 0.92 | D11: 0.48 | E11: 6.96 | F11: 6.1 | G11: 5.6
B12: Pretax Profit | C12: =C10-C11 -> 33.88 | D12: =D10-D11 -> 20.52 | E12: =E10-E11 -> 7.74 | F12: =F10-F11 -> 5.4 | G12: =G10-G11 -> 7.1
B13: Taxes | C13: 7.78 | D13: 4.97 | E13: 1.89 | F13: 1.41 | G13: 1.68
B14: Net Profit | C14: =C12-C13 -> 26.1 | D14: =D12-D13 -> 15.55 | E14: =E12-E13 -> 5.85 | F14: =F12-F13 -> 3.99 | G14: =G12-G13 -> 5.42
B17: Cash and Cash Equivalents | C17: 10.5 | D17: 9.8 | E17: 10.5 | F17: 10.4 | G17: 8.5
B18: Accounts Receivable | C18: 10 | D18: 9.7 | E18: 10.1 | F18: 13.8 | G18: 15
B19: Inventory | C19: 6.7 | D19: 7.7 | E19: 8.4 | F19: 10.9 | G19: 12
B20: Other Current Assets | C20: 3.6 | D20: 3.2 | E20: 4.6 | F20: 6.9 | G20: 7.7
B21: Current Assets | C21: =SUM(C17:C20) -> 30.8 | D21: =SUM(D17:D20) -> 30.4 | E21: =SUM(E17:E20) -> 33.6 | F21: =SUM(F17:F20) -> 42 | G21: =SUM(G17:G20) -> 43.2
B22: Net Property, Plant, and Equipment | C22: 92 | D22: 89.9 | E22: 264.4 | F22: 275.5 | G22: 289
B23: Other Fixed Assets | C23: 47.1 | D23: 47.6 | E23: 48.9 | F23: 46.6 | G23: 49.7
B24: Total Assets | C24: =C21+C22+C23 -> 169.9 | D24: =D21+D22+D23 -> 167.9 | E24: =E21+E22+E23 -> 346.9 | F24: =F21+F22+F23 -> 364.1 | G24: =G21+G22+G23 -> 381.9
B26: Accounts Payable | C26: 12.2 | D26: 13.4 | E26: 15.4 | F26: 14.4 | G26: 12.3
B27: Wages Payable | C27: 12.4 | D27: 14.4 | E27: 13.8 | F27: 13.7 | G27: 15
B28: Other Payables | C28: 8.1 | D28: 7.8 | E28: 5.6 | F28: 6.6 | G28: 8.3
B29: Current Liabilities | C29: =SUM(C26:C28) -> 32.7 | D29: =SUM(D26:D28) -> 35.6 | E29: =SUM(E26:E28) -> 34.8 | F29: =SUM(F26:F28) -> 34.7 | G29: =SUM(G26:G28) -> 35.6
B30: Debt | C30: 29.5 | D30: 9.05 | E30: 183 | F30: 196.31 | G30: 207.79
B31: Shareholders’ Equity | C31: 107.7 | D31: 123.25 | E31: 129.1 | F31: 133.09 | G31: 138.51
B32: Total Liabilities and Shareholders’ Equity | C32: =SUM(C29:C31) -> 169.9 | D32: =SUM(D29:D31) -> 167.9 | E32: =SUM(E29:E31) -> 346.9 | F32: =SUM(F29:F31) -> 364.1 | G32: =SUM(G29:G31) -> 381.9
A34: Source: All exhibits created by author.

Sheet Exhibit 2
A1: Exhibit 2
A2: Bob’s Baloney
A3: Benchmark Performance Figures for Sample of Premium Food Producers
A5: Financial Returns for Sample of Premium Food Producers for 2019
C7: ROE | D7: RONA
B8: Low-Return Firms (25th percentile) | C8: -0.012 | D8: 0.023
B9: Median-Return Firms (50th percentile) | C9: 0.089 | D9: 0.071
B10: High-Return Firms (75th percentile) | C10: 0.194 | D10: 0.133
A12: Capital Market Benchmarks for January 2020
B14: Estimated Cost of Equity (based on beta estimate of 0.9) | D14: 0.08
B15: Estimated Weighted Cost of Capital (WACC) | D15: 0.061
A17: Notes: ROE is net profit divided by shareholder’s equity.
B18: RONA (return on net assets) is NOPAT divided by net assets.
B19: NOPAT is net operating profit after tax.
B20: Net assets is net working capital plus PP&E.
B21: Net working capital is current operating assets less current operating liabilities.
B22: PP&E is net property, plant, and equipment.

Sheet Exhibit 3
A1: Exhibit 3
A2: Bob’s Baloney
A3: Spangler’s Financial Analysis of Bob’s Baloney
D5: 2015 | E5: 2016 | F5: 2017 | G5: 2018 | H5: 2019
B7: Growth and Returns
B8: Revenue Growth | C8: [percentage change in revenue] | D8: 0.055 | E8: ='Exhibit 1'!D6/'Exhibit 1'!C6-1 -> -0.025721785 | F8: ='Exhibit 1'!E6/'Exhibit 1'!D6-1 -> 0.13038793 | G8: ='Exhibit 1'!F6/'Exhibit 1'!E6-1 -> 0.1835081 | H8: ='Exhibit 1'!G6/'Exhibit 1'!F6-1 -> 0.094643576
B9: Return on Assets | C9: [net profit / total assets] | D9: ='Exhibit 1'!C14/'Exhibit 1'!C24 -> 0.15361978 | E9: ='Exhibit 1'!D14/'Exhibit 1'!D24 -> 0.092614652 | F9: ='Exhibit 1'!E14/'Exhibit 1'!E24 -> 0.016863649 | G9: ='Exhibit 1'!F14/'Exhibit 1'!F24 -> 0.010958528 | H9: ='Exhibit 1'!G14/'Exhibit 1'!G24 -> 0.014192197
B10: Return on Net Assets | C10: [NOPAT / net assets] | D10: =D32/D34 -> 0.19023324 | E10: =E32/E34 -> 0.11904762 | F10: =F32/F34 -> 0.035325216 | G10: =G32/G34 -> 0.026183971 | H10: =H32/H34 -> 0.027505053
B11: Return on Equity | C11: [net profit / shareholders’ equity] | D11: ='Exhibit 1'!C14/'Exhibit 1'!C31 -> 0.24233983 | E11: ='Exhibit 1'!D14/'Exhibit 1'!D31 -> 0.12616633 | F11: ='Exhibit 1'!E14/'Exhibit 1'!E31 -> 0.04531371 | G11: ='Exhibit 1'!F14/'Exhibit 1'!F31 -> 0.029979713 | H11: ='Exhibit 1'!G14/'Exhibit 1'!G31 -> 0.039130749
B14: Margins
B15: Gross Margin | C15: [gross profit / revenue] | D15: ='Exhibit 1'!C8/'Exhibit 1'!C6 -> 0.28136483 | E15: ='Exhibit 1'!D8/'Exhibit 1'!D6 -> 0.26831897 | F15: ='Exhibit 1'!E8/'Exhibit 1'!E6 -> 0.25262154 | G15: ='Exhibit 1'!F8/'Exhibit 1'!F6 -> 0.23761579 | H15: ='Exhibit 1'!G8/'Exhibit 1'!G6 -> 0.2196468
B16: SG&A Percentage | C16: [SG&A expenditures / revenue] | D16: ='Exhibit 1'!C9/'Exhibit 1'!C6 -> 0.098687664 | E16: ='Exhibit 1'!D9/'Exhibit 1'!D6 -> 0.15517241 | F16: ='Exhibit 1'!E9/'Exhibit 1'!E6 -> 0.18255481 | G16: ='Exhibit 1'!F9/'Exhibit 1'!F6 -> 0.19130085 | H16: ='Exhibit 1'!G9/'Exhibit 1'!G6 -> 0.17292127
B17: Operating Margin | C17: [operating profit / revenue] | D17: ='Exhibit 1'!C10/'Exhibit 1'!C6 -> 0.18267717 | E17: ='Exhibit 1'!D10/'Exhibit 1'!D6 -> 0.11314655 | F17: ='Exhibit 1'!E10/'Exhibit 1'!E6 -> 0.07006673 | G17: ='Exhibit 1'!F10/'Exhibit 1'!F6 -> 0.046314942 | H17: ='Exhibit 1'!G10/'Exhibit 1'!G6 -> 0.046725533
B18: Net Profit Margin | C18: [net profit / revenue] | D18: ='Exhibit 1'!C14/'Exhibit 1'!C6 -> 0.13700787 | E18: ='Exhibit 1'!D14/'Exhibit 1'!D6 -> 0.083782328 | F18: ='Exhibit 1'!E14/'Exhibit 1'!E6 -> 0.027883699 | G18: ='Exhibit 1'!F14/'Exhibit 1'!F6 -> 0.016069271 | H18: ='Exhibit 1'!G14/'Exhibit 1'!G6 -> 0.019941133
B20: Asset Efficiency
B21: Asset Turnover | C21: [revenue / total assets] | D21: ='Exhibit 1'!C6/'Exhibit 1'!C24 -> 1.1212478 | E21: ='Exhibit 1'!D6/'Exhibit 1'!D24 -> 1.1054199 | F21: ='Exhibit 1'!E6/'Exhibit 1'!E24 -> 0.60478524 | G21: ='Exhibit 1'!F6/'Exhibit 1'!F24 -> 0.68195551 | H21: ='Exhibit 1'!G6/'Exhibit 1'!G24 -> 0.71170463
B22: PPE Turnover | C22: [revenue / net PP&E] | D22: ='Exhibit 1'!C6/'Exhibit 1'!C22 -> 2.0706522 | E22: ='Exhibit 1'!D6/'Exhibit 1'!D22 -> 2.0645161 | F22: ='Exhibit 1'!E6/'Exhibit 1'!E22 -> 0.7934947 | G22: ='Exhibit 1'!F6/'Exhibit 1'!F22 -> 0.90127042 | H22: ='Exhibit 1'!G6/'Exhibit 1'!G22 -> 0.94048443
B23: NWC Turnover | C23: [revenue / net working capital] | D23: NA | E23: NA | F23: NA | G23: ='Exhibit 1'!F6/'Exhibit 3'!G33 -> 34.013699 | H23: ='Exhibit 1'!G6/'Exhibit 3'!H33 -> 35.763158
B24: AR Days (DSO) | C24: [accounts receivable / revenue × 365] | D24: ='Exhibit 1'!C18/'Exhibit 1'!C6*365 -> 19.160105 | E24: ='Exhibit 1'!D18/'Exhibit 1'!D6*365 -> 19.07597 | F24: ='Exhibit 1'!E18/'Exhibit 1'!E6*365 -> 17.571497 | G24: ='Exhibit 1'!F18/'Exhibit 1'!F6*365 -> 20.285944 | H24: ='Exhibit 1'!G18/'Exhibit 1'!G6*365 -> 20.143488
B25: Inv Days (DIO) | C25: [inventory / COGS × 365] | D25: ='Exhibit 1'!C19/'Exhibit 1'!C7*365 -> 17.863404 | E25: ='Exhibit 1'!D19/'Exhibit 1'!D7*365 -> 20.695876 | F25: ='Exhibit 1'!E19/'Exhibit 1'!E7*365 -> 19.553571 | G25: ='Exhibit 1'!F19/'Exhibit 1'!F7*365 -> 21.016904 | H25: ='Exhibit 1'!G19/'Exhibit 1'!G7*365 -> 20.650636
B26: AP Days (DPO) | C26: [accounts payable / COGS × 365] | D26: ='Exhibit 1'!C26/'Exhibit 1'!C7*365 -> 32.527392 | E26: ='Exhibit 1'!D26/'Exhibit 1'!D7*365 -> 36.0162 | F26: ='Exhibit 1'!E26/'Exhibit 1'!E7*365 -> 35.848214 | G26: ='Exhibit 1'!F26/'Exhibit 1'!F7*365 -> 27.765452 | H26: ='Exhibit 1'!G26/'Exhibit 1'!G7*365 -> 21.166902
B28: Leverage
B29: Debt / Total Capital | C29: [debt / (debt + shareholders’ equity)] | D29: ='Exhibit 1'!C30/('Exhibit 1'!C30+'Exhibit 1'!C31) -> 0.21501458 | E29: ='Exhibit 1'!D30/('Exhibit 1'!D30+'Exhibit 1'!D31) -> 0.06840514 | F29: ='Exhibit 1'!E30/('Exhibit 1'!E30+'Exhibit 1'!E31) -> 0.58635053 | G29: ='Exhibit 1'!F30/('Exhibit 1'!F30+'Exhibit 1'!F31) -> 0.59596236 | H29: ='Exhibit 1'!G30/('Exhibit 1'!G30+'Exhibit 1'!G31) -> 0.60002888
B31: Summary Accounts (in millions of US dollars)
B32: NOPAT (t = 25%) | C32: [operating profit × (1 − tax rate)] | D32: ='Exhibit 1'!C10*(1-0.25) -> 26.1 | E32: ='Exhibit 1'!D10*(1-0.25) -> 15.75 | F32: ='Exhibit 1'!E10*(1-0.25) -> 11.025 | G32: ='Exhibit 1'!F10*(1-0.25) -> 8.625 | H32: ='Exhibit 1'!G10*(1-0.25) -> 9.525
B33: Net Working Capital | C33: [current assets − current liabilities] | D33: ='Exhibit 1'!C21-'Exhibit 1'!C29 -> -1.9 | E33: ='Exhibit 1'!D21-'Exhibit 1'!D29 -> -5.2 | F33: ='Exhibit 1'!E21-'Exhibit 1'!E29 -> -1.2 | G33: ='Exhibit 1'!F21-'Exhibit 1'!F29 -> 7.3 | H33: ='Exhibit 1'!G21-'Exhibit 1'!G29 -> 7.6
B34: Net Assets | C34: [net working capital + net fixed assets] | D34: ='Exhibit 1'!C30+'Exhibit 1'!C31 -> 137.2 | E34: ='Exhibit 1'!D30+'Exhibit 1'!D31 -> 132.3 | F34: ='Exhibit 1'!E30+'Exhibit 1'!E31 -> 312.1 | G34: ='Exhibit 1'!F30+'Exhibit 1'!F31 -> 329.4 | H34: ='Exhibit 1'!G30+'Exhibit 1'!G31 -> 346.3
A37: Note: NOPAT is net operating profit after tax; SG&A is selling, general, and administrative expenses; PP&E is net property, plant, and equipment; NWC is net working capital; AR is accounts receivable; Inv is inventory; COGS is cost of goods sold; AP is accounts payable; DSO is days sales outstanding; DIO is days inventory outstanding; and DPO is day payables outstanding.
