Workbook

Sheet Cover
A1: ESBM4570
A2: Week 7 Example Financial Statements
A6: Created by: | B6: Ellen Burnes

Sheet Income Statement
B1: Tech Inc currently has 1000 shares of common stock outstanding
B4: Tech Inc Income Statement 2024
C5: $000s
B6: Revenue | C6: 2200
A7: - | B7: Cost of Good Sold | C7: 1000
B8: Gross Profit | C8: =C6-C7 -> 1200
A9: - | B9: SG&A | C9: 100
A10: - | B10: Other OPEX | C10: 227
A11: - | B11: Depreciation | C11: 94
B12: Operating Income = EBIT | C12: =C8-C9-C10-C11 -> 779
A13: - | B13: Interest Expense | C13: 20
B14: PreTax Income | C14: =C12-C13 -> 759
A15: - | B15: Taxes (18%) | C15: =0.18*C14 -> 136.62
B18: Net Income | C18: =C14-C15 -> 622.38
B21: Addition to Retained Earnings | C21: =C18-C22 -> 93.357
B22: Dividends | C22: =0.85*C18 -> 529.023 | E22: 85% payout

Sheet Balance Sheet
A1: TechInc Balance Sheet ($000s)
A2: ASSETS | F2: LIABILITIES & SHAREHOLDERS' EQUITY
B3: 2024 | C3: 2023 | G3: 2024 | H3: 2023
A4: Current Assets | F4: Current Liabilities
A5: Cash & equivalents | B5: =Cashflows!E29 -> 0 | C5: 107 | F5: Accounts Payable | G5: 213 | H5: 197
A6: Accounts Receivable | B6: 294 | C6: 270 | F6: Notes Payable | G6: 50 | H6: 53
A7: Inventories | B7: 269 | C7: 280 | F7: Accrued expenses | G7: 223 | H7: 205
A8: Other | B8: 68 | C8: 50
A9: Total Current Assets | B9: =SUM(B5:B8) -> 631 | C9: =SUM(C5:C8) -> 707 | F9: Total Current Liabilities | G9: =SUM(G5:G7) -> 486 | H9: =SUM(H5:H7) -> 455
A11: Fixed Assets | F11: Long-Term Liabilities
A12: PP&E | B12: 1423 | C12: 1274
A13: Less Accumulated Depreciation | B13: -554 | C13: -460 | F13: Long-term debt (Bonds) | G13: 465 | H13: 458
A14: Net PP&E | B14: =B12+B13 -> 869 | C14: =SUM(C12:C13) -> 814 | F14: Total long-term liabilities | G14: =G13 -> 465 | H14: =H13 -> 458
A15: Intangible Assets & Other | B15: 385 | C15: 221
A16: Total Fixed Assets | B16: =B14+B15 -> 1254 | C16: =C14+C15 -> 1035 | F16: Shareholders' Equity
F17: Common Stock ($1 par value) | G17: 486 | H17: =71+327 -> 398
F19: Accumulated Retained Earnings | G19: =H19+'Income Statement'!C21 -> 524.357 | H19: =347+84 -> 431
F21: Total Equity | G21: =G17+G19 -> 1010.357 | H21: =H17+H19 -> 829
A23: Total Assets | B23: =B9+B16 -> 1885 | C23: =C9+C16 -> 1742 | F23: Total Liabilities & Shareholders' Equity | G23: =G9+G14+G21 -> 1961.357 | H23: =H9+H14+H21 -> 1742
A28: NWC

Sheet Cashflows
E2: 2024
B3: Sources and Uses of Funds | C3: Which Financial Statement? | D3: Calculation | E3: Numbers
B4: Cashflows from Operating Activities
A5: + | B5: Net Income | C5: IS
A6: + | B6: Depreciation | C6: IS
A7: + | B7: Interest | C7: IS
A8: + | B8: Change in Accounts Payable | C8: BS | F8: When we talk about Working Capital Management, we are referring to this group
A9: - | B9: Change in Accounts Receivable | C9: BS
A10: - | B10: Change in Inventory | C10: BS
A11: + | B11: Change in Accrued Expenses | C11: BS
A12: - | B12: Change in Other | C12: BS
B13: Net Cashflow From Operations
B15: Cashflows from Long-term Investing Activities
A16: - | B16: Change in Fixed Assets | C16: BS
B17: Net Cashflow from Investing
B19: Cashflow to/from Financing
A20: + | B20: Change in Notes Payable | C20: BS
A21: + | B21: Change in Bonds | C21: BS
A22: + | B22: Change in Equity | C22: BS
A23: - | B23: Dividend Payment | C23: IS
A24: - | B24: Interest | C24: IS
A25: + | B25: Net Cashflow from financing
B27: Net Change in Cash
B28: Cash at Beginning of Year
B29: Cash at End of Year

Sheet wc and nwc
B2: 2023
B3: Calculations | C3: Current Assets | D3: Cash | E3: Current Liabilities | F3: Short Term Debt
A4: Inputs
A5: Working Capital
A6: Net Working Capital

Sheet EXAMPLE
B1: Year One | C1: Year Two | D1: NWC
D2: Averages
A3: Current Assets | B3: 450 | C3: 680
A4: Cash | B4: 80 | C4: 180
A5: Current Liabilities | B5: 185 | C5: 335
A6: Short Term Debt | B6: 0 | C6: 120
A7: NWC Average
A8: NWC Year 1 Actual
A9: NWC Year 2 Actual

Sheet EXAMPLE_ans
B1: Year One | C1: Year Two | D1: NWC
D2: Averages
A3: Current Assets | B3: 450 | C3: 680 | D3: =(C3+B3)/2 -> 565
A4: Cash | B4: 80 | C4: 180 | D4: =(C4+B4)/2 -> 130
A5: Current Liabilities | B5: 185 | C5: 335 | D5: =(C5+B5)/2 -> 260
A6: Short Term Debt | B6: 0 | C6: 120 | D6: =(C6+B6)/2 -> 60
A7: NWC Average | D7: =(D3-D4)-(D5-D6) -> 235
A8: NWC Year 1 Actual | B8: =(B3-B4)-(B5-B6) -> 185
A9: NWC Year 2 Actual | C9: =(C3-C4)-(C5-C6) -> 285

Sheet Net Cash Burn
B1: INCOME STATEMENT | G1: OPX | J1: INVESTMENT
B2: COGS + | C2: OPEX + | D2: R&D + | E2: INTEREST + | F2: TAXES + | G2: 🔼 Inventory - | H2: 🔼 in AP - | I2: 🔼 Other Liab + | J2: CAPEX
A3: Cash Burn =
B5: Revenue - | G5: 🔼 Receivables
A6: Cash Build =
A9: Net Burn | L9: < 0 means BUILDING THROUGH OPERATIONS/REVENUE

Sheet Net Cash Burn_ANS
B1: INCOME STATEMENT | G1: OPX | J1: INVESTMENT
B2: COGS + | C2: OPEX + | D2: R&D + | E2: INTEREST + | F2: TAXES + | G2: 🔼 Inventory - | H2: 🔼 in AP - | I2: 🔼 Other Liab + | J2: CAPEX
B3: Revenue - | G3: 🔼 Receivables
A4: Cash Build = | B4: ='Income Statement'!C6 -> 2200 | G4: =('Balance Sheet'!B6-'Balance Sheet'!C6) -> 24 | K4: =B4-G4 -> 2176
A6: Cash Burn = | B6: ='Income Statement'!C7 -> 1000 | C6: ='Income Statement'!C9+'Income Statement'!C10 -> 327 | D6: 0 | E6: ='Income Statement'!C13 -> 20 | F6: ='Income Statement'!C15 -> 136.62 | G6: =('Balance Sheet'!B7-'Balance Sheet'!C7) -> -11 | H6: =('Balance Sheet'!G5-'Balance Sheet'!H5) -> 16 | I6: =('Balance Sheet'!G6-'Balance Sheet'!H6)+('Balance Sheet'!G7-'Balance Sheet'!H7) -> 15 | J6: ='Balance Sheet'!B12-'Balance Sheet'!C12 -> 149 | K6: =B6+C6+D6+E6+F6+G6-H6-I6+J6 -> 1590.62
A12: Net Burn | K12: =K4-K6 -> 585.38 | L12: >0 means BUILDING THROUGH OPERATIONS/REVENUE
