Workbook

Sheet COVER page
A1: Case | B1: Bob's Baloney
A3: TEAM (1, 2 or 3)
A5: Bob Team Member Names
A11: Spangler Team Member Names
A17: Mino Team Member Names

Sheet Bobs Values
A1: 1
A2: Bob's Scorecard | B2: The scorecard below is how Bob's seems to be valuing itself, and judging its success factors. How do you see it weighting the categories, AND ranking itself.
B3: You may modify the categories.
A4: CURRENT
A5: Bucket | B5: Category | C5: Weight | D5: Ranking | E5: Value
A6: Financials | B6: Valuation based on Comps | E6: leave blank
A7: Team | B7: Team | E7: =C7*D7 -> 0
A8: Market | B8: Market Size | E8: =C8*D8 -> 0
A9: Market | B9: Competetive Environment | E9: =C9*D9 -> 0
A10: Market | B10: Marketing Impact | E10: =C10*D10 -> 0
A11: Product | B11: Product Quality | E11: =C11*D11 -> 0
A12: Market | B12: Reputation/Brand Alignment | E12: =C12*D12 -> 0
A13: Risk | B13: Risk
C15: =SUM(C7:C13) -> 0
B16: Weighted Scoreboard Multiplier | E16: =SUM(E7:E12) -> 0
B17: Scorecard Adjusted Valuation
A20: ?
A21: Community Service
A22: Best Employer
A23: Animal Rights
A24: Merch
A26: 2
A27: Based on Mino's input, Spangler's sense of issues, and YOUR understanding of value drivers, propose a Scorecard to Bob's
A28: RECOMMENDED
A29: Bucket | B29: Category | C29: Weight | D29: Ranking | E29: Value
A30: Financials | B30: Valuation based on Comps | E30: leave blank
E31: =C31*D31 -> 0
E32: =C32*D32 -> 0
E33: =C33*D33 -> 0
E34: =C34*D34 -> 0
E35: =C35*D35 -> 0
E36: =C36*D36 -> 0
C39: =SUM(C31:C37) -> 0
B40: Weighted Scoreboard Multiplier | E40: =SUM(E31:E36) -> 0

Sheet Bob Valuation
A1: On this page, we are using ASSUMPTIONS, to fill in the story of why is Mino so upset….
A2: YES, she holds 30% of the equity shares, so she likely has influence
A3: Let's develop what we DO know, to understand the impact of Bob's decision on the VALUE of INVESTOR's AUM (Assets Under Management)
B5: 2015 | C5: 2016 | D5: 2017 | E5: 2018 | F5: 2019
A6: NOPAT | B6: ='Exhibit 1_Fin Stmnt'!C14*(1-('Exhibit 1_Fin Stmnt'!C13/'Exhibit 1_Fin Stmnt'!C12)) -> 20.106553 | H6: NOPAT = | I6: Operating profits *(1-t)
A7: Multiple* | B7: 3
A9: Valuation
A11: Mino Paid Implied AUM | B11: =B9*0.3 -> 0 | F11: =0.3*F9 -> 0
A12: Gain/Loss | F12: =(F11/B11)-1 -> #DIV/0!
A15: * the multiple 3 is provided as an EXAMPLE.
A16: Assume that Mino buys in to Bobs in 2015 at the valuation you determin as a function of NOPAT and the Multiple given.
A17: She buys 30% of the company at this valuation.

Sheet Spangler DuPont
B6: DUPONT ANALYSIS OVER TIME
C7: 2015 | D7: 2016 | E7: 2017 | F7: 2018 | G7: 2019 | H7: % change (2015 to 2019)
B8: % Net Profit
B9: Asset Efficiency
B10: Equity Multiplier
B11: ROE
B15: Capital Structure Review
B16: D:E | C16: ='Exhibit 1_Fin Stmnt'!C30/'Exhibit 1_Fin Stmnt'!C31 -> 0.27390901 | D16: ='Exhibit 1_Fin Stmnt'!D30/'Exhibit 1_Fin Stmnt'!D31 -> 0.073427992 | E16: ='Exhibit 1_Fin Stmnt'!E30/'Exhibit 1_Fin Stmnt'!E31 -> 1.4175058 | F16: ='Exhibit 1_Fin Stmnt'!F30/'Exhibit 1_Fin Stmnt'!F31 -> 1.4750169 | G16: ='Exhibit 1_Fin Stmnt'!G30/'Exhibit 1_Fin Stmnt'!G31 -> 1.5001805
B17: % Debt
B18: % Equity
B21: Liquidity and Coverage
B22: Current Ratio | J22: Current Ratio = (Current Assets)/(Current Liabilities)
B23: Quick Ratio | J23: Quick Ratio = (Current Assets - Inventory)/(Current Liabilities)
B26: TIE | J26: TIE = Operating Profit/Interest

Sheet Mino Comps Eval
B2: Firms | C2: ROE | D2: RONA
A3: <25% | B3: Low Return Firms | C3: ='Exhibit 2_Benchmark'!C8 -> -0.012 | D3: 2.3
A5: <50% | B5: Median Return Firms | C5: ='Exhibit 2_Benchmark'!C9 -> 0.089 | D5: 0.071
A7: <75% | B7: High Return Firms | C7: ='Exhibit 2_Benchmark'!C10 -> 0.194 | D7: 0.133

Sheet Mino Return Metrics
B2: {=_xlfn.SEQUENCE(1,5,2015,1)} -> 2015 | C2: 2016 | D2: 2017 | E2: 2018 | F2: 2019
A3: Column1 | B3: Column2 | C3: Column3 | D3: Column4 | E3: Column5 | F3: Column6
A4: ROA
A5: Rev/Assets
A6: Rev/PPE | H6: **Note, In this case, they. Have included depreciation in SGA.
A7: ROSGA | H7: Marketing is included here
A9: Revenue % change
A10: Revenue | B10: ='Exhibit 1_Fin Stmnt'!C6 -> 190.5 | C10: ='Exhibit 1_Fin Stmnt'!D6 -> 185.6 | D10: ='Exhibit 1_Fin Stmnt'!E6 -> 209.8 | E10: ='Exhibit 1_Fin Stmnt'!F6 -> 248.3 | F10: ='Exhibit 1_Fin Stmnt'!G6 -> 271.8

Sheet Exhibit 1_Fin Stmnt
A1: Exhibit 1
A2: Bob’s Baloney
A3: Financial Statements for Bob’s Baloney (in millions of US dollars)
C5: 2015 | D5: 2016 | E5: 2017 | F5: 2018 | G5: 2019 | H5: 2015 | I5: 2016 | J5: 2017 | K5: 2018 | L5: 2019
B6: Revenue | C6: 190.5 | D6: 185.6 | E6: 209.8 | F6: 248.3 | G6: 271.8
B7: Cost of Goods Sold | C7: 136.9 | D7: 135.8 | E7: 156.8 | F7: 189.3 | G7: 212.1
B8: Gross Profit | C8: =C6-C7 -> 53.6 | D8: =D6-D7 -> 49.8 | E8: =E6-E7 -> 53 | F8: =F6-F7 -> 59 | G8: =G6-G7 -> 59.7 | H8: =C8/C6 -> 0.28136483 | I8: =D8/D6 -> 0.26831897 | J8: =E8/E6 -> 0.25262154 | K8: =F8/F6 -> 0.23761579 | L8: =G8/G6 -> 0.2196468
B9: Selling and General Expenses | C9: 18.8 | D9: 28.8 | E9: 38.3 | F9: 47.5 | G9: 47
B10: Operating Profit | C10: =C8-C9 -> 34.8 | D10: =D8-D9 -> 21 | E10: =E8-E9 -> 14.7 | F10: =F8-F9 -> 11.5 | G10: =G8-G9 -> 12.7 | H10: =C10/C6 -> 0.18267717 | I10: =D10/D6 -> 0.11314655 | J10: =E10/E6 -> 0.07006673 | K10: =F10/F6 -> 0.046314942 | L10: =G10/G6 -> 0.046725533
B11: Net Interest Expense | C11: 0.92 | D11: 0.48 | E11: 6.96 | F11: 6.1 | G11: 5.6
B12: Pretax Profit | C12: =C10-C11 -> 33.88 | D12: =D10-D11 -> 20.52 | E12: =E10-E11 -> 7.74 | F12: =F10-F11 -> 5.4 | G12: =G10-G11 -> 7.1
B13: Taxes | C13: 7.78 | D13: 4.97 | E13: 1.89 | F13: 1.41 | G13: 1.68
B14: Net Profit | C14: =C12-C13 -> 26.1 | D14: =D12-D13 -> 15.55 | E14: =E12-E13 -> 5.85 | F14: =F12-F13 -> 3.99 | G14: =G12-G13 -> 5.42
B17: Cash and Cash Equivalents | C17: 10.5 | D17: 9.8 | E17: 10.5 | F17: 10.4 | G17: 8.5
B18: Accounts Receivable | C18: 10 | D18: 9.7 | E18: 10.1 | F18: 13.8 | G18: 15
B19: Inventory | C19: 6.7 | D19: 7.7 | E19: 8.4 | F19: 10.9 | G19: 12
B20: Other Current Assets | C20: 3.6 | D20: 3.2 | E20: 4.6 | F20: 6.9 | G20: 7.7
B21: Current Assets | C21: =SUM(C17:C20) -> 30.8 | D21: =SUM(D17:D20) -> 30.4 | E21: =SUM(E17:E20) -> 33.6 | F21: =SUM(F17:F20) -> 42 | G21: =SUM(G17:G20) -> 43.2
B22: Net Property, Plant, and Equipment | C22: 92 | D22: 89.9 | E22: 264.4 | F22: 275.5 | G22: 289
B23: Other Fixed Assets | C23: 47.1 | D23: 47.6 | E23: 48.9 | F23: 46.6 | G23: 49.7
B24: Total Assets | C24: =C21+C22+C23 -> 169.9 | D24: =D21+D22+D23 -> 167.9 | E24: =E21+E22+E23 -> 346.9 | F24: =F21+F22+F23 -> 364.1 | G24: =G21+G22+G23 -> 381.9
B26: Accounts Payable | C26: 12.2 | D26: 13.4 | E26: 15.4 | F26: 14.4 | G26: 12.3
B27: Wages Payable | C27: 12.4 | D27: 14.4 | E27: 13.8 | F27: 13.7 | G27: 15
B28: Other Payables | C28: 8.1 | D28: 7.8 | E28: 5.6 | F28: 6.6 | G28: 8.3
B29: Current Liabilities | C29: =SUM(C26:C28) -> 32.7 | D29: =SUM(D26:D28) -> 35.6 | E29: =SUM(E26:E28) -> 34.8 | F29: =SUM(F26:F28) -> 34.7 | G29: =SUM(G26:G28) -> 35.6
B30: Debt | C30: 29.5 | D30: 9.05 | E30: 183 | F30: 196.31 | G30: 207.79
B31: Shareholders’ Equity | C31: 107.7 | D31: 123.25 | E31: 129.1 | F31: 133.09 | G31: 138.51
B32: Total Liabilities and Shareholders’ Equity | C32: =SUM(C29:C31) -> 169.9 | D32: =SUM(D29:D31) -> 167.9 | E32: =SUM(E29:E31) -> 346.9 | F32: =SUM(F29:F31) -> 364.1 | G32: =SUM(G29:G31) -> 381.9
A34: Source: All exhibits created by author.

Sheet Exhibit 2_Benchmark
A1: Exhibit 2
A2: Bob’s Baloney
A3: Benchmark Performance Figures for Sample of Premium Food Producers
A5: Financial Returns for Sample of Premium Food Producers for 2019
C7: ROE | D7: RONA
B8: Low-Return Firms (25th percentile) | C8: -0.012 | D8: 0.023
B9: Median-Return Firms (50th percentile) | C9: 0.089 | D9: 0.071
B10: High-Return Firms (75th percentile) | C10: 0.194 | D10: 0.133
A12: Capital Market Benchmarks for January 2020
B14: Estimated Cost of Equity (based on beta estimate of 0.9) | D14: 0.08
B15: Estimated Weighted Cost of Capital (WACC) | D15: 0.061
A17: Notes: ROE is net profit divided by shareholder’s equity.
B18: RONA (return on net assets) is NOPAT divided by net assets.
B19: NOPAT is net operating profit after tax.
B20: Net assets is net working capital plus PP&E.
B21: Net working capital is current operating assets less current operating liabilities.
B22: PP&E is net property, plant, and equipment.

Sheet Exhibit 3+Analysis
A1: Exhibit 3
A2: Bob’s Baloney
A3: Spangler’s Financial Analysis of Bob’s Baloney
D5: 2015 | E5: 2016 | F5: 2017 | G5: 2018 | H5: 2019
B7: Growth and Returns
B8: Revenue Growth | C8: [percentage change in revenue] | D8: 0.055 | E8: ='Exhibit 1_Fin Stmnt'!D6/'Exhibit 1_Fin Stmnt'!C6-1 -> -0.025721785 | F8: ='Exhibit 1_Fin Stmnt'!E6/'Exhibit 1_Fin Stmnt'!D6-1 -> 0.13038793 | G8: ='Exhibit 1_Fin Stmnt'!F6/'Exhibit 1_Fin Stmnt'!E6-1 -> 0.1835081 | H8: ='Exhibit 1_Fin Stmnt'!G6/'Exhibit 1_Fin Stmnt'!F6-1 -> 0.094643576
B9: Return on Assets | C9: [net profit / total assets] | D9: ='Exhibit 1_Fin Stmnt'!C14/'Exhibit 1_Fin Stmnt'!C24 -> 0.15361978 | E9: ='Exhibit 1_Fin Stmnt'!D14/'Exhibit 1_Fin Stmnt'!D24 -> 0.092614652 | F9: ='Exhibit 1_Fin Stmnt'!E14/'Exhibit 1_Fin Stmnt'!E24 -> 0.016863649 | G9: ='Exhibit 1_Fin Stmnt'!F14/'Exhibit 1_Fin Stmnt'!F24 -> 0.010958528 | H9: ='Exhibit 1_Fin Stmnt'!G14/'Exhibit 1_Fin Stmnt'!G24 -> 0.014192197
B10: Return on Net Assets | C10: [NOPAT / net assets] | D10: =D32/D34 -> 0.19023324 | E10: =E32/E34 -> 0.11904762 | F10: =F32/F34 -> 0.035325216 | G10: =G32/G34 -> 0.026183971 | H10: =H32/H34 -> 0.027505053
B11: Return on Equity | C11: [net profit / shareholders’ equity] | D11: ='Exhibit 1_Fin Stmnt'!C14/'Exhibit 1_Fin Stmnt'!C31 -> 0.24233983 | E11: ='Exhibit 1_Fin Stmnt'!D14/'Exhibit 1_Fin Stmnt'!D31 -> 0.12616633 | F11: ='Exhibit 1_Fin Stmnt'!E14/'Exhibit 1_Fin Stmnt'!E31 -> 0.04531371 | G11: ='Exhibit 1_Fin Stmnt'!F14/'Exhibit 1_Fin Stmnt'!F31 -> 0.029979713 | H11: ='Exhibit 1_Fin Stmnt'!G14/'Exhibit 1_Fin Stmnt'!G31 -> 0.039130749
B14: Margins
B15: Gross Margin | C15: [gross profit / revenue] | D15: ='Exhibit 1_Fin Stmnt'!C8/'Exhibit 1_Fin Stmnt'!C6 -> 0.28136483 | E15: ='Exhibit 1_Fin Stmnt'!D8/'Exhibit 1_Fin Stmnt'!D6 -> 0.26831897 | F15: ='Exhibit 1_Fin Stmnt'!E8/'Exhibit 1_Fin Stmnt'!E6 -> 0.25262154 | G15: ='Exhibit 1_Fin Stmnt'!F8/'Exhibit 1_Fin Stmnt'!F6 -> 0.23761579 | H15: ='Exhibit 1_Fin Stmnt'!G8/'Exhibit 1_Fin Stmnt'!G6 -> 0.2196468
B16: SG&A Percentage | C16: [SG&A expenditures / revenue] | D16: ='Exhibit 1_Fin Stmnt'!C9/'Exhibit 1_Fin Stmnt'!C6 -> 0.098687664 | E16: ='Exhibit 1_Fin Stmnt'!D9/'Exhibit 1_Fin Stmnt'!D6 -> 0.15517241 | F16: ='Exhibit 1_Fin Stmnt'!E9/'Exhibit 1_Fin Stmnt'!E6 -> 0.18255481 | G16: ='Exhibit 1_Fin Stmnt'!F9/'Exhibit 1_Fin Stmnt'!F6 -> 0.19130085 | H16: ='Exhibit 1_Fin Stmnt'!G9/'Exhibit 1_Fin Stmnt'!G6 -> 0.17292127
B17: Operating Margin | C17: [operating profit / revenue] | D17: ='Exhibit 1_Fin Stmnt'!C10/'Exhibit 1_Fin Stmnt'!C6 -> 0.18267717 | E17: ='Exhibit 1_Fin Stmnt'!D10/'Exhibit 1_Fin Stmnt'!D6 -> 0.11314655 | F17: ='Exhibit 1_Fin Stmnt'!E10/'Exhibit 1_Fin Stmnt'!E6 -> 0.07006673 | G17: ='Exhibit 1_Fin Stmnt'!F10/'Exhibit 1_Fin Stmnt'!F6 -> 0.046314942 | H17: ='Exhibit 1_Fin Stmnt'!G10/'Exhibit 1_Fin Stmnt'!G6 -> 0.046725533
B18: Net Profit Margin | C18: [net profit / revenue] | D18: ='Exhibit 1_Fin Stmnt'!C14/'Exhibit 1_Fin Stmnt'!C6 -> 0.13700787 | E18: ='Exhibit 1_Fin Stmnt'!D14/'Exhibit 1_Fin Stmnt'!D6 -> 0.083782328 | F18: ='Exhibit 1_Fin Stmnt'!E14/'Exhibit 1_Fin Stmnt'!E6 -> 0.027883699 | G18: ='Exhibit 1_Fin Stmnt'!F14/'Exhibit 1_Fin Stmnt'!F6 -> 0.016069271 | H18: ='Exhibit 1_Fin Stmnt'!G14/'Exhibit 1_Fin Stmnt'!G6 -> 0.019941133
B20: Asset Efficiency
B21: Asset Turnover | C21: [revenue / total assets] | D21: ='Exhibit 1_Fin Stmnt'!C6/'Exhibit 1_Fin Stmnt'!C24 -> 1.1212478 | E21: ='Exhibit 1_Fin Stmnt'!D6/'Exhibit 1_Fin Stmnt'!D24 -> 1.1054199 | F21: ='Exhibit 1_Fin Stmnt'!E6/'Exhibit 1_Fin Stmnt'!E24 -> 0.60478524 | G21: ='Exhibit 1_Fin Stmnt'!F6/'Exhibit 1_Fin Stmnt'!F24 -> 0.68195551 | H21: ='Exhibit 1_Fin Stmnt'!G6/'Exhibit 1_Fin Stmnt'!G24 -> 0.71170463
B22: PPE Turnover | C22: [revenue / net PP&E] | D22: ='Exhibit 1_Fin Stmnt'!C6/'Exhibit 1_Fin Stmnt'!C22 -> 2.0706522 | E22: ='Exhibit 1_Fin Stmnt'!D6/'Exhibit 1_Fin Stmnt'!D22 -> 2.0645161 | F22: ='Exhibit 1_Fin Stmnt'!E6/'Exhibit 1_Fin Stmnt'!E22 -> 0.7934947 | G22: ='Exhibit 1_Fin Stmnt'!F6/'Exhibit 1_Fin Stmnt'!F22 -> 0.90127042 | H22: ='Exhibit 1_Fin Stmnt'!G6/'Exhibit 1_Fin Stmnt'!G22 -> 0.94048443
B23: NWC Turnover | C23: [revenue / net working capital] | D23: NA | E23: NA | F23: NA | G23: ='Exhibit 1_Fin Stmnt'!F6/'Exhibit 3+Analysis'!G33 -> 34.013699 | H23: ='Exhibit 1_Fin Stmnt'!G6/'Exhibit 3+Analysis'!H33 -> 35.763158
B24: AR Days (DSO) | C24: [accounts receivable / revenue × 365] | D24: ='Exhibit 1_Fin Stmnt'!C18/'Exhibit 1_Fin Stmnt'!C6*365 -> 19.160105 | E24: ='Exhibit 1_Fin Stmnt'!D18/'Exhibit 1_Fin Stmnt'!D6*365 -> 19.07597 | F24: ='Exhibit 1_Fin Stmnt'!E18/'Exhibit 1_Fin Stmnt'!E6*365 -> 17.571497 | G24: ='Exhibit 1_Fin Stmnt'!F18/'Exhibit 1_Fin Stmnt'!F6*365 -> 20.285944 | H24: ='Exhibit 1_Fin Stmnt'!G18/'Exhibit 1_Fin Stmnt'!G6*365 -> 20.143488
B25: Inv Days (DIO) | C25: [inventory / COGS × 365] | D25: ='Exhibit 1_Fin Stmnt'!C19/'Exhibit 1_Fin Stmnt'!C7*365 -> 17.863404 | E25: ='Exhibit 1_Fin Stmnt'!D19/'Exhibit 1_Fin Stmnt'!D7*365 -> 20.695876 | F25: ='Exhibit 1_Fin Stmnt'!E19/'Exhibit 1_Fin Stmnt'!E7*365 -> 19.553571 | G25: ='Exhibit 1_Fin Stmnt'!F19/'Exhibit 1_Fin Stmnt'!F7*365 -> 21.016904 | H25: ='Exhibit 1_Fin Stmnt'!G19/'Exhibit 1_Fin Stmnt'!G7*365 -> 20.650636
B26: AP Days (DPO) | C26: [accounts payable / COGS × 365] | D26: ='Exhibit 1_Fin Stmnt'!C26/'Exhibit 1_Fin Stmnt'!C7*365 -> 32.527392 | E26: ='Exhibit 1_Fin Stmnt'!D26/'Exhibit 1_Fin Stmnt'!D7*365 -> 36.0162 | F26: ='Exhibit 1_Fin Stmnt'!E26/'Exhibit 1_Fin Stmnt'!E7*365 -> 35.848214 | G26: ='Exhibit 1_Fin Stmnt'!F26/'Exhibit 1_Fin Stmnt'!F7*365 -> 27.765452 | H26: ='Exhibit 1_Fin Stmnt'!G26/'Exhibit 1_Fin Stmnt'!G7*365 -> 21.166902
B28: Leverage
B29: Debt / Total Capital | C29: [debt / (debt + shareholders’ equity)] | D29: ='Exhibit 1_Fin Stmnt'!C30/('Exhibit 1_Fin Stmnt'!C30+'Exhibit 1_Fin Stmnt'!C31) -> 0.21501458 | E29: ='Exhibit 1_Fin Stmnt'!D30/('Exhibit 1_Fin Stmnt'!D30+'Exhibit 1_Fin Stmnt'!D31) -> 0.06840514 | F29: ='Exhibit 1_Fin Stmnt'!E30/('Exhibit 1_Fin Stmnt'!E30+'Exhibit 1_Fin Stmnt'!E31) -> 0.58635053 | G29: ='Exhibit 1_Fin Stmnt'!F30/('Exhibit 1_Fin Stmnt'!F30+'Exhibit 1_Fin Stmnt'!F31) -> 0.59596236 | H29: ='Exhibit 1_Fin Stmnt'!G30/('Exhibit 1_Fin Stmnt'!G30+'Exhibit 1_Fin Stmnt'!G31) -> 0.60002888
B31: Summary Accounts (in millions of US dollars)
B32: NOPAT (t = 25%) | C32: [operating profit × (1 − tax rate)] | D32: ='Exhibit 1_Fin Stmnt'!C10*(1-0.25) -> 26.1 | E32: ='Exhibit 1_Fin Stmnt'!D10*(1-0.25) -> 15.75 | F32: ='Exhibit 1_Fin Stmnt'!E10*(1-0.25) -> 11.025 | G32: ='Exhibit 1_Fin Stmnt'!F10*(1-0.25) -> 8.625 | H32: ='Exhibit 1_Fin Stmnt'!G10*(1-0.25) -> 9.525
B33: Net Working Capital | C33: [current assets − current liabilities] | D33: ='Exhibit 1_Fin Stmnt'!C21-'Exhibit 1_Fin Stmnt'!C29 -> -1.9 | E33: ='Exhibit 1_Fin Stmnt'!D21-'Exhibit 1_Fin Stmnt'!D29 -> -5.2 | F33: ='Exhibit 1_Fin Stmnt'!E21-'Exhibit 1_Fin Stmnt'!E29 -> -1.2 | G33: ='Exhibit 1_Fin Stmnt'!F21-'Exhibit 1_Fin Stmnt'!F29 -> 7.3 | H33: ='Exhibit 1_Fin Stmnt'!G21-'Exhibit 1_Fin Stmnt'!G29 -> 7.6
B34: Net Assets | C34: [net working capital + net fixed assets] | D34: ='Exhibit 1_Fin Stmnt'!C30+'Exhibit 1_Fin Stmnt'!C31 -> 137.2 | E34: ='Exhibit 1_Fin Stmnt'!D30+'Exhibit 1_Fin Stmnt'!D31 -> 132.3 | F34: ='Exhibit 1_Fin Stmnt'!E30+'Exhibit 1_Fin Stmnt'!E31 -> 312.1 | G34: ='Exhibit 1_Fin Stmnt'!F30+'Exhibit 1_Fin Stmnt'!F31 -> 329.4 | H34: ='Exhibit 1_Fin Stmnt'!G30+'Exhibit 1_Fin Stmnt'!G31 -> 346.3
A37: Note: NOPAT is net operating profit after tax; SG&A is selling, general, and administrative expenses; PP&E is net property, plant, and equipment; NWC is net working capital; AR is accounts receivable; Inv is inventory; COGS is cost of goods sold; AP is accounts payable; DSO is days sales outstanding; DIO is days inventory outstanding; and DPO is day payables outstanding.

Sheet Title Page
B2: This spreadsheet supports STUDENT analysis of the case “Bob’s Baloney” (UVA-F-1942).
A4: This spreadsheet was prepared by Michael Schill, Sponsors Professor of Business Administration. Copyright © 2020 by the University of Virginia Darden School Foundation, Charlottesville, VA. All rights reserved. For customer service inquiries, send an email tosales@dardenbusinesspublishing.com. No part of this publication may be reproduced, stored in a retrieval system, posted to the internet, or transmitted in any form or by any means—electronic, mechanical, photocopying, recording, or otherwise—without the permission of the Darden School Foundation. This publication is protected by copyright and may not be uploaded in whole or part to any AI, large language model, or similar system, or to any related database. Our goal is to publish materials of the highest quality, so please submit any errata to editorial@dardenbusinesspublishing.com.
A5: Rev. Jan. 30, 2024
