Workbook

Sheet COVER
A1: DCF
A2: Week12.2
A4: Ellen Burnes

Sheet PV
A1: Example 1
A2: N
A3: r
A4: PV
A5: PMT
A6: FV
A8: Example 2
A9: N
A10: r
A11: PV
A12: PMT
A13: FV
B15: 0 | C15: 1 | D15: 2 | E15: 3 | F15: 4 | G15: 5 | H15: 6 | I15: 7 | J15: 8 | K15: 9 | L15: 10
A16: Cash Flow
A17: PV by year
A18: PV
A19: r | B19: 0.08

Sheet NPV
A1: Year | B1: Cashflows
A2: 1 | B2: 10000
A3: 2 | B3: 12000
A4: 3 | B4: 25000
A5: 4 | B5: 45000
A6: 5 | B6: 75000
A8: r | B8: 0.09
A9: NPV

Sheet Perpetuity
A1: Example 4
A3: PMT | B3: 1525
A4: r | B4: 0.12
A5: PV

Sheet PF_BS
A1: Year | B1: 1 | C1: 2 | D1: 3 | E1: 4 | F1: 5 | I1: Assumptions: | J1: 1 | M1: 1 | N1: Forecast | O1: 2 | P1: 3 | Q1: 4 | R1: 5
A2: Revenue | B2: 325000 | C2: =B2*(1+$J$2) -> 438750 | D2: =C2*(1+$J$2) -> 592312.5 | E2: =D2*(1+$J$2) -> 799621.88 | F2: =E2*(1+$J$2) -> 1079489.5 | I2: Growth | J2: 0.35 | L2: Current Assets | N2: * year 2 sales
A3: COGS | B3: =B2*$J$3 -> 130000 | C3: =C2*$J$3 -> 175500 | D3: =D2*$J$3 -> 236925 | E3: =E2*$J$3 -> 319848.75 | F3: =F2*$J$3 -> 431795.81 | I3: COGS (as % of Revenue) | J3: 0.4 | L3: Cash | M3: 6500 | N3: 0.12
A4: Gross Profit | B4: =B2-B3 -> 195000 | C4: =C2-C3 -> 263250 | D4: =D2-D3 -> 355387.5 | E4: =E2-E3 -> 479773.12 | F4: =F2-F3 -> 647693.72 | I4: OPEX | L4: A/R | M4: 25000 | N4: 0.25
A5: OPEX | I5: Mktng | J5: 0.3 | L5: Inventories | M5: 15000 | N5: 0.25
A6: Mktng | B6: =B2*$J$5 -> 97500 | C6: =C2*$J$5 -> 131625 | D6: =D2*$J$5 -> 177693.75 | E6: =E2*$J$5 -> 239886.56 | F6: =F2*$J$5 -> 323846.86 | I6: Other Overhead | J6: 0.06 | L6: Total Current Assets | M6: =SUM(M3:M5) -> 46500
A7: Other OH | B7: 20000 | C7: =B7*(1+$J$6) -> 21200 | D7: =C7*(1+$J$6) -> 22472 | E7: =D7*(1+$J$6) -> 23820.32 | F7: =E7*(1+$J$6) -> 25249.539 | I7: Depreciation | J7: 0.01
A8: EBITDA | B8: =B4-B6-B7 -> 77500 | C8: =C4-C6-C7 -> 110425 | D8: =D4-D6-D7 -> 155221.75 | E8: =E4-E6-E7 -> 216066.24 | F8: =F4-F6-F7 -> 298597.32 | I8: Interest | J8: 0 | L8: Fixed Assets
A9: Depreciation | B9: 13000 | C9: =B9*(1+$J$7) -> 13130 | D9: =C9*(1+$J$7) -> 13261.3 | E9: =D9*(1+$J$7) -> 13393.913 | F9: =E9*(1+$J$7) -> 13527.852 | I9: Taxes | J9: 0.25 | L9: PP&E Gross | M9: 55000 | N9: 0.15
A10: EBIT | B10: =B8-B9 -> 64500 | C10: =C8-C9 -> 97295 | D10: =D8-D9 -> 141960.45 | E10: =E8-E9 -> 202672.33 | F10: =F8-F9 -> 285069.47 | L10: Acc Dep | M10: 13000
A11: Interest | B11: =$J$9 -> 0.25 | C11: =$J$9 -> 0.25 | D11: =$J$9 -> 0.25 | E11: =$J$9 -> 0.25 | F11: =$J$9 -> 0.25 | L11: PP&E Net | M11: =M9-M10 -> 42000
A12: Pre Tax Profit | B12: =B10-B11 -> 64499.75 | C12: =C10-C11 -> 97294.75 | D12: =D10-D11 -> 141960.2 | E12: =E10-E11 -> 202672.08 | F12: =F10-F11 -> 285069.22 | L12: Total Assets | M12: =M6+M11 -> 88500
A13: Taxes | B13: =B12*$J$9 -> 16124.938 | C13: =C12*$J$9 -> 24323.688 | D13: =D12*$J$9 -> 35490.05 | E13: =E12*$J$9 -> 50668.02 | F13: =F12*$J$9 -> 71267.305
A14: Net Income | B14: =B12-B13 -> 48374.812 | C14: =C12-C13 -> 72971.062 | D14: =D12-D13 -> 106470.15 | E14: =E12-E13 -> 152004.06 | F14: =F12-F13 -> 213801.91 | L14: Liabilities & SE
L15: Current Liabilities
L16: A/P | M16: 30000 | N16: 0.05
L17: Bank Note/Loan | M17: 0
L18: Total Current Liabilities | M18: =M16+M17 -> 30000
L20: Long Term Liabilities
L21: Bank Loan | M21: 0
L23: Equity
L24: Invested Capital | M24: 10125
L25: Retained Earnings | M25: =#REF! -> #REF!
L26: Total Equity | M26: =M24+M25 -> #REF!
L27: AFN | M27: 0
L28: Total Liabilities & SE | M28: =M18+M21+M26 -> #REF!
L30: Liabilities&SE +AFN

Sheet DCF
A1: $000s | C1: PROJECTIONS
A2: Net Income | B2: 1 | C2: 2 | D2: 3 | E2: 4 | F2: 5
A3: Revenue | B3: =PF_BS!B2 -> 325000 | C3: =PF_BS!C2 -> 438750 | D3: =PF_BS!D2 -> 592312.5 | E3: =PF_BS!E2 -> 799621.88 | F3: =PF_BS!F2 -> 1079489.5
A4: COGS | B4: =PF_BS!B3 -> 130000 | C4: =PF_BS!C3 -> 175500 | D4: =PF_BS!D3 -> 236925 | E4: =PF_BS!E3 -> 319848.75 | F4: =PF_BS!F3 -> 431795.81
A5: Gross Profit | B5: =B3-B4 -> 195000 | C5: =C3-C4 -> 263250 | D5: =D3-D4 -> 355387.5 | E5: =E3-E4 -> 479773.12 | F5: =F3-F4 -> 647693.72
A6: OPEX (SG&A) | B6: =PF_BS!B6+PF_BS!B7 -> 117500 | C6: =PF_BS!C6+PF_BS!C7 -> 152825 | D6: =PF_BS!D6+PF_BS!D7 -> 200165.75 | E6: =PF_BS!E6+PF_BS!E7 -> 263706.88 | F6: =PF_BS!F6+PF_BS!F7 -> 349096.4
A7: EBITDA | B7: =B5-B6 -> 77500 | C7: =C5-C6 -> 110425 | D7: =D5-D6 -> 155221.75 | E7: =E5-E6 -> 216066.24 | F7: =F5-F6 -> 298597.32
A8: Depreciation | B8: =PF_BS!B9 -> 13000 | C8: =PF_BS!C9 -> 13130 | D8: =PF_BS!D9 -> 13261.3 | E8: =PF_BS!E9 -> 13393.913 | F8: =PF_BS!F9 -> 13527.852
A9: EBIT | B9: =B7-B8 -> 64500 | C9: =C7-C8 -> 97295 | D9: =D7-D8 -> 141960.45 | E9: =E7-E8 -> 202672.33 | F9: =F7-F8 -> 285069.47
A10: Interest | B10: 0 | C10: 0 | D10: 0 | E10: 0 | F10: 0
A11: EBT | B11: =B9-B10 -> 64500 | C11: =C9-C10 -> 97295 | D11: =D9-D10 -> 141960.45 | E11: =E9-E10 -> 202672.33 | F11: =F9-F10 -> 285069.47
A12: Taxes | B12: =PF_BS!B13 -> 16124.938 | C12: =PF_BS!C13 -> 24323.688 | D12: =PF_BS!D13 -> 35490.05 | E12: =PF_BS!E13 -> 50668.02 | F12: =PF_BS!F13 -> 71267.305
A13: Net Income | B13: =B11-B12 -> 48375.062 | C13: =C11-C12 -> 72971.312 | D13: =D11-D12 -> 106470.4 | E13: =E11-E12 -> 152004.31 | F13: =F11-F12 -> 213802.16
A16: NWC
A17: Req Cash + AR + Inv | I17: required cash = | J17: 0.2
A18: A/P
A19: NWC
A20: CHANGE in NWC
A23: CAPEX
A24: PP&E Gross
A27: CHANGE in CAPEX
A30: Operating FCF | I30: cost of capital, r = | J30: 0.3
A31: Terminal Value | I31: long term growth, g = | J31: 0.1
A33: Total FCF
A35: NPV
A48: Total Liabilities
A50: Invested Capital
A51: Retained Earnings
A52: Total Equity
A54: Total Liabilities & SE
A57: CASH
A58: Required Cash + AR + Inv | B58: 50000
A59: AP + Accrual | B59: 25
