Workbook

Sheet Balance Sheet
A1: NOTE THE ORDER OF 2020 AND 2021 BELOW. BE SURE AND TAKE CHANGES ACCORDINGLY
A2: BALANCE SHEET
A3: Assets | E3: Liabilities & Shareholders Equity
B4: 2020 | C4: 2021 | F4: 2020 | G4: 2021
A5: Current Assets | E5: Current Liabilities
A6: Cash | B6: 50000 | E6: Accounts Payable | F6: 130000 | G6: 160000
A7: Accounts Receivable | B7: 200000 | C7: 280000 | E7: Note Payable | F7: 90000 | G7: 100000
A8: Inventories | B8: 400000 | C8: 500000 | E8: Accrued Liabilities | F8: 50000 | G8: 70000
A9: Current Assets | B9: =SUM(B6:B8) -> 650000 | C9: =SUM(C6:C8) -> 780000 | E9: Current Liabilities | F9: =SUM(F6:F8) -> 270000 | G9: =SUM(G6:G8) -> 330000
A11: Fixed Assets | E11: Long Term Liabilities
A12: Gross Fixed Assets | B12: 450000 | C12: 540000 | E12: Long Term Debt | F12: 300000 | G12: 400000
A13: Accumulated Depreciation | B13: 100000 | C13: 140000 | E13: Long Term Liabilities | F13: =F12 -> 300000 | G13: =G12 -> 400000
A14: Net Fixed Assets | B14: =B12-B13 -> 350000 | C14: =C12-C13 -> 400000 | E14: Equity
E15: Common Stock | F15: 350000 | G15: 350000
E16: Retained Earnings | F16: 80000
E17: Total Equity | F17: =SUM(F15:F16) -> 430000 | G17: =SUM(G15:G16) -> 350000
A19: Total Assets | E19: Total L & SE | F19: =SUM(F9+F13+F17) -> 1000000 | G19: =SUM(G9+G13+G17) -> 1080000

Sheet Income Statement
A1: Income Statement 2021
A2: Revenue | B2: 1500000
A3: COGS | B3: 900000
A4: Gross Profit
A5: OPEX | B5: 400000
A6: EBITDA
A7: Depreciation | B7: 40000
A8: EBIT
A9: Interest | B9: 65000
A10: Pre Tax Income
A11: Taxes (30%)
A12: Net Income
A14: Dividiend Payout = $0

Sheet Statement of Cash Flows
E2: 2021
B3: Sources and Uses of Funds | C3: Which Financial Statement? | D3: Calculation | E3: Numbers
B4: Cashflows from Operating Activities
A5: + | B5: Net Income | C5: IS
A6: + | B6: Depreciation | C6: IS
A7: + | B7: Interest | C7: IS
A8: + | B8: Change in Accounts Payable | C8: BS | F8: When we talk about Working Capital Management, we are referring to this group
A9: - | B9: Change in Accounts Receivable | C9: BS
A10: - | B10: Change in Inventory | C10: BS
A11: + | B11: Change in Accrued Liabilities | C11: BS
A12: - | B12: Change in Other | C12: BS | E12: NA
B13: Net Cashflow From Operations
B15: Cashflows from Long-term Investing Activities
A16: - | B16: Change in Fixed Assets | C16: BS
B17: Net Cashflow from Investing
B19: Cashflow to/from Financing
A20: + | B20: Change in Notes Payable | C20: BS
A21: + | B21: Change in Bonds | C21: BS
A22: + | B22: Change in Equity (STOCK) | C22: BS
A23: - | B23: Dividend Payment | C23: IS
A24: - | B24: Interest | C24: IS
A25: + | B25: Net Cashflow from financing
B27: Net Change in Cash
B28: Cash at Beginning of Year
B29: Cash at End of Year

Sheet Burn-Build
B1: INCOME STATEMENT | G1: OPX | J1: INVESTMENT
B2: COGS + | C2: OPEX + | D2: INTEREST + | E2: TAXES + | F2: Other + | G2: 🔼 Inventory - | H2: 🔼 in AP - | I2: 🔼 Other Liab + | J2: R&D+ | K2: CAPEX
A3: Cash Burn =
B5: Revenue - | G5: 🔼 Receivables
A6: Cash Build =
A9: Net Burn | M9: < 0 means BUILDING CASH THROUGH OPERATIONS/REVENUE
M10: > 0 means BURNING CASH THROUGH OPERATIONS/REVENUE

Sheet Working Capital
A2: Working Capital | B2: = Current Assets - Current Liabilities
A3: Net Working Capital = | C3: (Current Assets - Cash) - (Current Liabilities - Notes Payable)
B5: 2020 | C5: 2021
A6: WC
A7: NWC

Sheet Balance Sheet_ANS
A1: NOTE THE ORDER OF 2020 AND 2021 BELOW. BE SURE AND TAKE CHANGES ACCORDINGLY
A2: BALANCE SHEET
A3: Assets | E3: Liabilities & Shareholders Equity
B4: 2020 | C4: 2021 | F4: 2020 | G4: 2021
A5: Current Assets | E5: Current Liabilities
A6: Cash | B6: 50000 | C6: ='Statement of Cash Flows_ANS'!E29 -> 46500 | E6: Accounts Payable | F6: 130000 | G6: 160000
A7: Accounts Receivable | B7: 200000 | C7: 280000 | E7: Note Payable | F7: 90000 | G7: 100000
A8: Inventories | B8: 400000 | C8: 500000 | E8: Accrued Liabilities | F8: 50000 | G8: 70000
A9: Current Assets | B9: =SUM(B6:B8) -> 650000 | C9: =SUM(C6:C8) -> 826500 | E9: Current Liabilities | F9: =SUM(F6:F8) -> 270000 | G9: =SUM(G6:G8) -> 330000
A11: Fixed Assets | E11: Long Term Liabilities
A12: Gross Fixed Assets | B12: 450000 | C12: 540000 | E12: Long Term Debt | F12: 300000 | G12: 400000
A13: Accumulated Depreciation | B13: 100000 | C13: 140000 | E13: Long Term Liabilities | F13: =F12 -> 300000 | G13: =G12 -> 400000
A14: Net Fixed Assets | B14: =B12-B13 -> 350000 | C14: =C12-C13 -> 400000 | E14: Equity
E15: Common Stock | F15: 350000 | G15: 350000
E16: Retained Earnings | F16: 80000 | G16: =F16+'Income Statement_ANS'!B12 -> 146500
E17: Total Equity | F17: =SUM(F15:F16) -> 430000 | G17: =SUM(G15:G16) -> 496500
A19: Total Assets | B19: =B9+B14 -> 1000000 | C19: =C9+C14 -> 1226500 | E19: Total L & SE | F19: =SUM(F9+F13+F17) -> 1000000 | G19: =SUM(G9+G13+G17) -> 1226500

Sheet Income Statement_ANS
A1: Income Statement 2021
A2: Revenue | B2: 1500000
A3: COGS | B3: 900000
A4: Gross Profit | B4: =B2-B3 -> 600000
A5: OPEX | B5: 400000
A6: EBITDA | B6: =B4-B5 -> 200000
A7: Depreciation | B7: 40000
A8: EBIT | B8: =B6-B7 -> 160000
A9: Interest | B9: 65000
A10: Pre Tax Income | B10: =B8-B9 -> 95000
A11: Taxes (30%) | B11: =0.3*B10 -> 28500
A12: Net Income | B12: =B10-B11 -> 66500
A14: Dividiend Payout = $0

Sheet Statement of Cash Flows_ANS
E2: 2021
B3: Sources and Uses of Funds | C3: Which Financial Statement? | D3: Calculation | E3: Numbers
B4: Cashflows from Operating Activities
A5: + | B5: Net Income | C5: IS | E5: ='Income Statement_ANS'!B12 -> 66500
A6: + | B6: Depreciation | C6: IS | E6: ='Income Statement_ANS'!B7 -> 40000
A7: + | B7: Interest | C7: IS | E7: ='Income Statement_ANS'!B9 -> 65000
A8: + | B8: Change in Accounts Payable | C8: BS | E8: =('Balance Sheet_ANS'!G6-'Balance Sheet_ANS'!F6) -> 30000 | F8: When we talk about Working Capital Management, we are referring to this group
A9: - | B9: Change in Accounts Receivable | C9: BS | E9: ='Balance Sheet_ANS'!C7-'Balance Sheet_ANS'!B7 -> 80000
A10: - | B10: Change in Inventory | C10: BS | E10: ='Balance Sheet_ANS'!C8-'Balance Sheet_ANS'!B8 -> 100000
A11: + | B11: Change in Accrued Liabilities | C11: BS | E11: ='Balance Sheet_ANS'!G8-'Balance Sheet_ANS'!F8 -> 20000
A12: - | B12: Change in Other | C12: BS | E12: NA
B13: Net Cashflow From Operations | E13: =E5+E6+E7+E8-E9-E10+E11 -> 41500
B15: Cashflows from Long-term Investing Activities
A16: - | B16: Change in Fixed Assets | C16: BS | E16: ='Balance Sheet_ANS'!C12-'Balance Sheet_ANS'!B12 -> 90000
B17: Net Cashflow from Investing | E17: =-E16 -> -90000
B19: Cashflow to/from Financing
A20: + | B20: Change in Notes Payable | C20: BS | E20: ='Balance Sheet_ANS'!G7-'Balance Sheet_ANS'!F7 -> 10000
A21: + | B21: Change in Bonds | C21: BS | E21: ='Balance Sheet_ANS'!G13-'Balance Sheet_ANS'!F13 -> 100000
A22: + | B22: Change in Equity (STOCK) | C22: BS | E22: ='Balance Sheet_ANS'!G15-'Balance Sheet_ANS'!F15 -> 0
A23: - | B23: Dividend Payment | C23: IS | E23: 0
A24: - | B24: Interest | C24: IS | E24: ='Income Statement_ANS'!B9 -> 65000
A25: + | B25: Net Cashflow from financing | E25: =E20+E21+E22-E23-E24 -> 45000
B27: Net Change in Cash | E27: =E13+E17+E25 -> -3500
B28: Cash at Beginning of Year | E28: ='Balance Sheet_ANS'!B6 -> 50000
B29: Cash at End of Year | E29: =E27+E28 -> 46500

Sheet Burn-Build_ANS
B1: INCOME STATEMENT | G1: OPX | J1: INVESTMENT
B2: COGS + | C2: OPEX + | D2: INTEREST + | E2: TAXES + | F2: Other + | G2: 🔼 Inventory - | H2: 🔼 in AP - | I2: 🔼 Other Liab + | J2: R&D+ | K2: CAPEX
A3: Cash Burn = | B3: ='Income Statement_ANS'!B3 -> 900000 | C3: ='Income Statement_ANS'!B5 -> 400000 | D3: ='Income Statement_ANS'!B9 -> 65000 | E3: ='Income Statement_ANS'!B11 -> 28500 | G3: =('Balance Sheet_ANS'!C8-'Balance Sheet_ANS'!B8) -> 100000 | H3: ='Balance Sheet_ANS'!G6-'Balance Sheet_ANS'!F6 -> 30000 | I3: ='Balance Sheet_ANS'!G8-'Balance Sheet_ANS'!F8 -> 20000 | K3: ='Balance Sheet_ANS'!C12-'Balance Sheet_ANS'!B12 -> 90000 | L3: =B3+C3+D3+E3+F3+G3-H3-I3+J3+K3 -> 1533500
B5: Revenue - | G5: 🔼 Receivables
A6: Cash Build = | B6: ='Income Statement_ANS'!B2 -> 1500000 | G6: ='Balance Sheet_ANS'!C7-'Balance Sheet_ANS'!B7 -> 80000 | L6: =B6-G6 -> 1420000
A9: Net Burn | L9: =L3-L6 -> 113500 | M9: < 0 means BUILDING CASH THROUGH OPERATIONS/REVENUE
M10: > 0 means BURNING CASH THROUGH OPERATIONS/REVENUE

Sheet Working Capital_ANS
A2: Working Capital | B2: = Current Assets - Current Liabilities
A3: Net Working Capital = | C3: (Current Assets - Cash) - (Current Liabilities - Notes Payable)
B5: 2020 | C5: 2021
A6: WC | B6: ='Balance Sheet_ANS'!B9-'Balance Sheet_ANS'!F9 -> 380000 | C6: ='Balance Sheet_ANS'!C9-'Balance Sheet_ANS'!G9 -> 496500
A7: NWC | B7: 420000 | C7: =('Balance Sheet_ANS'!C9-'Balance Sheet_ANS'!C6)-('Balance Sheet_ANS'!G9-'Balance Sheet_ANS'!G7) -> 550000
